LICENSE
setup.py
django_viewssi.egg-info/PKG-INFO
django_viewssi.egg-info/SOURCES.txt
django_viewssi.egg-info/dependency_links.txt
django_viewssi.egg-info/not-zip-safe
django_viewssi.egg-info/top_level.txt
viewssi/__init__.py
viewssi/templatetags/__init__.py
viewssi/templatetags/viewssi.py