Metadata-Version: 1.0
Name: django-viewssi
Version: 0.1.1
Summary: Template tag for requesting views in templates (Django)
Home-page: http://pypi.python.org/pypi/django-viewssi
Author: Tamas Kemenczy
Author-email: tamas.kemenczy@gmail.com
License: BSD
Keywords: django utilities templatetag
Platform: UNKNOWN
Classifier: Development Status :: 2 - Pre-Alpha
Classifier: Environment :: Web Environment
Classifier: Framework :: Django
Classifier: Intended Audience :: Developers
Classifier: License :: OSI Approved :: BSD License
Classifier: Operating System :: OS Independent
Classifier: Programming Language :: Python
